Metadata-Version: 2.1
Name: pom-elements
Version: 0.1.0
Summary: The Python Page Object Model that extends to Page Elements
Home-page: https://github.com/nickbeaird/pom-elements
Author: Nick Beaird
Author-email: nicklasbeaird@gmail.com
License: UNKNOWN
Platform: UNKNOWN
Classifier: Programming Language :: Python :: 3
Classifier: License :: OSI Approved :: MIT License
Classifier: Operating System :: OS Independent
Requires-Python: >=3.7
